warprnnt_numba/__init__.py
warprnnt_numba/numba_utils.py
warprnnt_numba/package_info.py
warprnnt_numba/rnnt_loss/__init__.py
warprnnt_numba/rnnt_loss/rnnt.py
warprnnt_numba/rnnt_loss/rnnt_numpy.py
warprnnt_numba/rnnt_loss/rnnt_pytorch.py
warprnnt_numba/rnnt_loss/rnnt_atomic_locks/__init__.py
warprnnt_numba/rnnt_loss/rnnt_atomic_locks/rnnt_atomic_locks.py
warprnnt_numba/rnnt_loss/rnnt_atomic_locks/rnnt_atomic_locks_pytorch.py
warprnnt_numba/rnnt_loss/rnnt_atomic_locks/utils/__init__.py
warprnnt_numba/rnnt_loss/rnnt_atomic_locks/utils/naive_gpu_rnnt.py
warprnnt_numba/rnnt_loss/rnnt_atomic_locks/utils/naive_gpu_rnnt_kernel.py
warprnnt_numba/rnnt_loss/utils/__init__.py
warprnnt_numba/rnnt_loss/utils/global_constants.py
warprnnt_numba/rnnt_loss/utils/rnnt_helper.py
warprnnt_numba/rnnt_loss/utils/cpu_utils/__init__.py
warprnnt_numba/rnnt_loss/utils/cpu_utils/cpu_rnnt.py
warprnnt_numba/rnnt_loss/utils/cuda_utils/__init__.py
warprnnt_numba/rnnt_loss/utils/cuda_utils/gpu_rnnt.py
warprnnt_numba/rnnt_loss/utils/cuda_utils/gpu_rnnt_kernel.py
warprnnt_numba/rnnt_loss/utils/cuda_utils/reduce.py
warprnnt_numba-0.4.1.dist-info/LICENSE
warprnnt_numba-0.4.1.dist-info/METADATA
warprnnt_numba-0.4.1.dist-info/WHEEL
warprnnt_numba-0.4.1.dist-info/top_level.txt
warprnnt_numba-0.4.1.dist-info/RECORD
