Metadata-Version: 2.1
Name: warprnnt-numba
Version: 0.4.1
Summary: Warp RNNT loss ported to Numba for faster experimentation
Home-page: https://github.com/titu1994/warprnnt_numba
Download-URL: https://github.com/titu1994/warprnnt_numba
Author: Somshubra Majumdar
Author-email: titu1994@gmail.com
License: MIT
Platform: UNKNOWN
Classifier: Programming Language :: Python :: 3
Classifier: Programming Language :: Python :: 3.7
Classifier: Programming Language :: Python :: 3.8
Classifier: License :: OSI Approved :: MIT License
Classifier: Operating System :: OS Independent
Classifier: Topic :: Software Development :: Libraries
Classifier: Topic :: Software Development :: Libraries :: Python Modules
Requires-Python: >=3.7.0
License-File: LICENSE
Provides-Extra: cpu
Requires-Dist: pytorch ; extra == 'cpu'
Provides-Extra: gpu
Requires-Dist: pytorch ; extra == 'gpu'
Provides-Extra: tests
Requires-Dist: pytest ; extra == 'tests'
